[
  {
    "method": "zero_shot",
    "bridge_em": 0.32673267326732675,
    "bridge_n": 404,
    "comparison_em": 0.4791666666666667,
    "comparison_n": 96,
    "total_em": 0.356,
    "total_n": 500
  },
  {
    "method": "standard_cot",
    "bridge_em": 0.2698019801980198,
    "bridge_n": 404,
    "comparison_em": 0.5,
    "comparison_n": 96,
    "total_em": 0.314,
    "total_n": 500
  },
  {
    "method": "gers",
    "bridge_em": 0.33663366336633666,
    "bridge_n": 404,
    "comparison_em": 0.6770833333333334,
    "comparison_n": 96,
    "total_em": 0.402,
    "total_n": 500
  }
]